pgsequelize/__init__.py
pgsequelize/execute.py
pgsequelize/main.py
pgsequelize/query.py
pgsequelize-0.0.5.dist-info/METADATA
pgsequelize-0.0.5.dist-info/WHEEL
pgsequelize-0.0.5.dist-info/top_level.txt
pgsequelize-0.0.5.dist-info/RECORD
