Metadata-Version: 2.1
Name: pgsequelize
Version: 0.0.5
Summary: FlaskPostgresSequelize
Author: Rahil Patel (TechAddict)
Author-email: <rahil.geek21@outlook.com>
Keywords: python,flask,postgres,database,sql,sequelize
Classifier: Development Status :: 1 - Planning
Classifier: Intended Audience :: Developers
Classifier: Programming Language :: Python :: 3
Classifier: Operating System :: Unix
Classifier: Operating System :: MacOS :: MacOS X
Classifier: Operating System :: Microsoft :: Windows
Requires-Dist: psycopg2
